phonexia_voice_activity_detection_client.py
phonexia_voice_activity_detection_client-2.1.0.dist-info/METADATA
phonexia_voice_activity_detection_client-2.1.0.dist-info/WHEEL
phonexia_voice_activity_detection_client-2.1.0.dist-info/entry_points.txt
phonexia_voice_activity_detection_client-2.1.0.dist-info/top_level.txt
phonexia_voice_activity_detection_client-2.1.0.dist-info/RECORD
